task1/rom.sv
module rom #(
    parameter   ADDRESS_WIDTH = 8,
                DATA_WIDTH = 8
)(
    input logic clk,
    input logic [ADDRESS_WIDTH-1:0] addr,
    output logic [DATA_WIDTH-1:0] dout
);

logic [DATA_WIDTH-1:0] rom_array [2 ** ADDRESS_WIDTH-1:0];

initial begin
        $display("Loading rom.");
        $readmemh("sinerom.mem", rom_array);
end;

always_ff @(posedge clk)
    // output is synchronous
    dout <= rom_array [addr];

endmodule

task1/counter.sv
module counter #(
    parameter WIDTH = 8
)(
    // interface signals
    input logic              clk,
    input logic              rst,
    input logic              en,
    input logic  [WIDTH-1:0] incr,
    output logic [WIDTH-1:0] count
);

always_ff @(posedge clk)
    if (rst)     count <= {WIDTH{1'b0}};
    // value of count is set to value of count + en, which if 0 will not change anything, otherwise be 1, incremeneting, as required.
    else if (en) count <= count + incr;
endmodule

task1/sinegen.sv
module sinegen #(
    parameter   A_WIDTH = 8,
                D_WIDTH = 8
)(
    // interface signals
    input   logic               clk,
    input   logic               rst,
    input   logic               en,
    input   logic [D_WIDTH-1:0] incr,
    output  logic [D_WIDTH-1:0] dout
);

    logic [A_WIDTH-1:0] address; // interconnect wire

counter addrCounter (
    .clk (clk),
    .rst (rst),
    .en (en),
    .incr (incr),
    .count (address)
);

rom sineRom (
    .clk (clk),
    .addr (address),
    .dout (dout)
);

endmodule

task1/sinegen.vcd
$version Generated by VerilatedVcd $end
$date Fri Nov  4 01:24:53 2022 $end
$timescale 1ps $end

 $scope module TOP $end
  $var wire  1 # clk $end
  $var wire  8 ' dout [7:0] $end
  $var wire  1 % en $end
  $var wire  8 & incr [7:0] $end
  $var wire  1 $ rst $end
  $scope module sinegen $end
   $var wire 32 ) A_WIDTH [31:0] $end
   $var wire 32 ) D_WIDTH [31:0] $end
   $var wire  8 ( address [7:0] $end
   $var wire  1 # clk $end
   $var wire  8 ' dout [7:0] $end
   $var wire  1 % en $end
   $var wire  8 & incr [7:0] $end
   $var wire  1 $ rst $end
   $scope module addrCounter $end
    $var wire 32 ) WIDTH [31:0] $end
    $var wire  1 # clk $end
    $var wire  8 ( count [7:0] $end
    $var wire  1 % en $end
    $var wire  8 & incr [7:0] $end
    $var wire  1 $ rst $end
   $upscope $end
   $scope module sineRom $end
    $var wire 32 ) ADDRESS_WIDTH [31:0] $end
    $var wire 32 ) DATA_WIDTH [31:0] $end
    $var wire  8 ( addr [7:0] $end
    $var wire  1 # clk $end
    $var wire  8 ' dout [7:0] $end
   $upscope $end
  $upscope $end
 $upscope $end
$enddefinitions $end


#0
1#
0$
1%
b00000001 &
b00000000 '
b00000000 (
b00000000000000000000000000001000 )
#1
0#
#2
1#
b00110011 &
b11111110 '
b00000001 (
#3
0#
#4
1#
b00110001 &
b11111101 '
b00110100 (
#5
0#
#6
1#
b00101111 &
b10100011 '
b01100101 (
#7
0#
#8
1#
b00101101 &
b00011010 '
b10010100 (
#9
0#
#10
1#
b00001110 '
b11000001 (
#11
0#
#12
1#
b10000010 '
b11101110 (
#13
0#
#14
1#
b11110001 '
b00011011 (
#15
0#
#16
1#
b11100011 '
b01001000 (
#17
0#
#18
1#
b01100110 '
b01110101 (
#19
0#
#20
1#
b00000100 '
b10100010 (
#21
0#
#22
1#
b00101001 '
b11001111 (
#23
0#
#24
1#
b10101100 '
b11111100 (
#25
0#
#26
1#
b11111101 '
b00101001 (
#27
0#
#28
1#
b11000010 '
b01010110 (
#29
0#
#30
1#
b00111101 '
b10000011 (
#31
0#
#32
1#
b00000000 '
b10110000 (
#33
0#
#34
1#
b01001110 '
b11011101 (
#35
0#
#36
1#
b11010001 '
b00001010 (
#37
0#
#38
1#
b11111010 '
b00110111 (
#39
0#
#40
1#
b10011010 '
b01100100 (
#41
0#
#42
1#
b00011100 '
b10010001 (
#43
0#
#44
1#
b00001010 '
b10111110 (
#45
0#
#46
1#
b01111000 '
b11101011 (
#47
0#
#48
1#
b11101101 '
b00011000 (
#49
0#
#50
1#
b11101000 '
b01000101 (
#51
0#
#52
1#
b00101100 &
b01101111 '
b01110010 (
#53
0#
#54
1#
b00000111 '
b10011110 (
#55
0#
#56
1#
b00101011 &
b00100000 '
b11001010 (
#57
0#
#58
1#
b00100111 &
b10011101 '
b11110101 (
#59
0#
#60
1#
b00100101 &
b11111001 '
b00011100 (
#61
0#
#62
1#
b11100001 '
b01000001 (
#63
0#
#64
1#
b01111011 '
b01100110 (
#65
0#
#66
1#
b00011000 '
b10001011 (
#67
0#
#68
1#
b00000100 '
b10110000 (
#69
0#
#70
1#
b01001110 '
b11010101 (
#71
0#
#72
1#
b10111101 '
b11111010 (
#73
0#
#74
1#
b11111100 '
b00011111 (
#75
0#
#76
1#
b11011010 '
b01000100 (
#77
0#
#78
1#
b01110010 '
b01101001 (
#79
0#
#80
1#
b00010011 '
b10001110 (
#81
0#
#82
1#
b00000111 '
b10110011 (
#83
0#
#84
1#
b01010111 '
b11011000 (
#85
0#
#86
1#
b00100100 &
b11000101 '
b11111101 (
#87
0#
#88
1#
b00100010 &
b11111101 '
b00100001 (
#89
0#
#90
1#
b00100001 &
b11010110 '
b01000011 (
#91
0#
#92
1#
b00011101 &
b01110101 '
b01100100 (
#93
0#
#94
1#
b00011011 &
b00011100 '
b10000001 (
#95
0#
#96
1#
b00000000 '
b10011100 (
#97
0#
#98
1#
b00011100 '
b10110111 (
#99
0#
#100
1#
b01100011 '
b11010010 (
#101
0#
#102
1#
b10110101 '
b11101101 (
#103
0#
#104
1#
b11110000 '
b00001000 (
#105
0#
#106
1#
b11111011 '
b00100011 (
#107
0#
#108
1#
b11010001 '
b00111110 (
#109
0#
#110
1#
b10000101 '
b01011001 (
#111
0#
#112
1#
b00110101 '
b01110100 (
#113
0#
#114
1#
b00000101 '
b10001111 (
#115
0#
#116
1#
b00011010 &
b00001000 '
b10101010 (
#117
0#
#118
1#
b00011000 &
b00111101 '
b11000100 (
#119
0#
#120
1#
b00010110 &
b10001011 '
b11011100 (
#121
0#
#122
1#
b00010001 &
b11001111 '
b11110010 (
#123
0#
#124
1#
b00010000 &
b11110110 '
b00000011 (
#125
0#
#126
1#
b11111101 '
b00010011 (
#127
0#
#128
1#
b11110000 '
b00100011 (
#129
0#
#130
1#
b11010001 '
b00110011 (
#131
0#
#132
1#
b10100110 '
b01000011 (
#133
0#
#134
1#
b01110101 '
b01010011 (
#135
0#
#136
1#
b01000101 '
b01100011 (
#137
0#
#138
1#
b00011110 '
b01110011 (
#139
0#
#140
1#
b00000110 '
b10000011 (
#141
0#
#142
1#
b00000000 '
b10010011 (
#143
0#
#144
1#
b00001101 '
b10100011 (
#145
0#
#146
1#
b00101100 '
b10110011 (
#147
0#
#148
1#
b01010111 '
b11000011 (
#149
0#
#150
1#
b10001000 '
b11010011 (
#151
0#
#152
1#
b10111000 '
b11100011 (
#153
0#
#154
1#
b11011111 '
b11110011 (
#155
0#
#156
1#
b11110111 '
b00000011 (
#157
0#
#158
1#
b11111101 '
b00010011 (
#159
0#
#160
1#
b11110000 '
b00100011 (
#161
0#
#162
1#
b00001111 &
b11010001 '
b00110011 (
#163
0#
#164
1#
b00001100 &
b10100110 '
b01000010 (
#165
0#
#166
1#
b00000110 &
b01111000 '
b01001110 (
#167
0#
#168
1#
b00000011 &
b01010100 '
b01010100 (
#169
0#
#170
1#
b01000011 '
b01010111 (
#171
0#
#172
1#
b00111011 '
b01011010 (
#173
0#
#174
1#
b00110011 '
b01011101 (
#175
0#
#176
1#
b00101100 '
b01100000 (
#177
0#
#178
1#
b00100101 '
b01100011 (
#179
0#
#180
1#
b00011110 '
b01100110 (
#181
0#
#182
1#
b00011000 '
b01101001 (
#183
0#
#184
1#
b00010011 '
b01101100 (
#185
0#
#186
1#
b00001110 '
b01101111 (
#187
0#
#188
1#
b00001010 '
b01110010 (
#189
0#
#190
1#
b00000111 '
b01110101 (
#191
0#
#192
1#
b00000100 '
b01111000 (
#193
0#
#194
1#
b00000010 '
b01111011 (
#195
0#
#196
1#
b00000000 '
b01111110 (
#197
0#
#198
1#
b10000001 (
#199
0#
#200
1#
b10000100 (
#201
0#
#202
1#
b10000111 (
#203
0#
#204
1#
b00000001 '
b10001010 (
#205
0#
#206
1#
b00000011 '
b10001101 (
#207
0#
#208
1#
b00000110 '
b10010000 (
#209
0#
#210
1#
b00001001 '
b10010011 (
#211
0#
#212
1#
b00001101 '
b10010110 (
#213
0#
#214
1#
b00000010 &
b00010010 '
b10011001 (
#215
0#
#216
1#
b00000000 &
b00010111 '
b10011011 (
#217
0#
#218
1#
b00011010 '
